fruitbat/__init__.py
fruitbat/__version__.py
fruitbat/_frb.py
fruitbat/catalogue.py
fruitbat/cosmologies.py
fruitbat/methods.py
fruitbat/plot.py
fruitbat/table.py
fruitbat/utils.py
fruitbat/data/Batten2021.hdf5
fruitbat/data/Inoue2004.hdf5
fruitbat/data/Inoue2004_EAGLE.npz
fruitbat/data/Inoue2004_Planck13.npz
fruitbat/data/Inoue2004_Planck15.npz
fruitbat/data/Inoue2004_Planck18.npz
fruitbat/data/Inoue2004_WMAP5.npz
fruitbat/data/Inoue2004_WMAP7.npz
fruitbat/data/Inoue2004_WMAP9.npz
fruitbat/data/Ioka2003.hdf5
fruitbat/data/Ioka2003_EAGLE.npz
fruitbat/data/Ioka2003_Planck13.npz
fruitbat/data/Ioka2003_Planck15.npz
fruitbat/data/Ioka2003_Planck18.npz
fruitbat/data/Ioka2003_WMAP5.npz
fruitbat/data/Ioka2003_WMAP7.npz
fruitbat/data/Ioka2003_WMAP9.npz
fruitbat/data/Zhang2018.hdf5
fruitbat/data/Zhang2018_EAGLE.npz
fruitbat/data/Zhang2018_Planck13.npz
fruitbat/data/Zhang2018_Planck15.npz
fruitbat/data/Zhang2018_Planck18.npz
fruitbat/data/Zhang2018_WMAP5.npz
fruitbat/data/Zhang2018_WMAP7.npz
fruitbat/data/Zhang2018_WMAP9.npz
fruitbat/data/frbcat_database_20190408.csv
fruitbat/data/pytest_output_simple_dm.hdf5
fruitbat/tests/__init__.py
fruitbat/tests/test_fruitbat_regression.py
fruitbat/tests/test_fruitbat_unit.py
fruitbat-2.0.1.dist-info/LICENSE
fruitbat-2.0.1.dist-info/METADATA
fruitbat-2.0.1.dist-info/WHEEL
fruitbat-2.0.1.dist-info/top_level.txt
fruitbat-2.0.1.dist-info/RECORD
