Metadata-Version: 2.1
Name: fruitbat
Version: 2.0.1
Summary: Calculate the redshift of a FRB from its dispersion measure
Home-page: https://github.com/abatten/fruitbat
Author: Adam Batten
Author-email: adamjbatten@gmail.com
License: UNKNOWN
Download-URL: https://pypi.org/project/fruitbat
Project-URL: Documentation, https://fruitbat.readthedocs.io
Project-URL: Source Code, https://github.com/abatten/fruitbat
Keywords: FRB redshift astronomy astrophysics fast radio burst
Platform: UNKNOWN
Classifier: Programming Language :: Python :: 3
Classifier: Programming Language :: Python :: 3.5
Classifier: Programming Language :: Python :: 3.6
Classifier: Programming Language :: Python :: 3.7
Classifier: Programming Language :: Python :: 3.8
Classifier: License :: OSI Approved :: BSD License
Classifier: Operating System :: MacOS
Classifier: Operating System :: Unix
Requires-Dist: numpy (>=1.16.0)
Requires-Dist: scipy (>=1.0.0)
Requires-Dist: astropy (>=3.2.3)
Requires-Dist: matplotlib (>=2.2.4)
Requires-Dist: pandas (>=0.22.0)
Requires-Dist: e13tools (>=0.5.3)
Requires-Dist: pygedm (>=3.2.3)
Requires-Dist: h5py (>=2.10.0)
